venny4py/__init__.py
venny4py/venny4py.py
venny4py-1.0.3.dist-info/METADATA
venny4py-1.0.3.dist-info/WHEEL
venny4py-1.0.3.dist-info/licenses/LICENSE
venny4py-1.0.3.dist-info/RECORD
