Metadata-Version: 2.3
Name: venny4py
Version: 1.0.3
Summary: Python3 package to create Venn diagrams with 2-4 sets.
Project-URL: Homepage, https://github.com/timyerg/venny4py
Project-URL: Bug Tracker, https://github.com/timyerg/venny4py/issues
Author-email: Timur Yergaliyev <timyerg@gmail.com>
License-File: LICENSE
Classifier: License :: OSI Approved :: MIT License
Classifier: Operating System :: OS Independent
Classifier: Programming Language :: Python :: 3
Requires-Python: >=3.7
